sioba_serial/__init__.py
sioba_serial/interface/__init__.py
sioba_serial-0.1.20251002.dist-info/WHEEL
sioba_serial-0.1.20251002.dist-info/entry_points.txt
sioba_serial-0.1.20251002.dist-info/METADATA
sioba_serial-0.1.20251002.dist-info/RECORD
