Metadata-Version: 2.3
Name: sioba-serial
Version: 0.1.20251002
Summary: Sioba Websocket IO Interface layer
Author: Aki Mimoto
Author-email: Aki Mimoto <aki@bako.ca>
License: MIT License
Classifier: License :: OSI Approved :: MIT License
Requires-Dist: sioba>=0.6
Requires-Dist: loguru>=0.7.2
Requires-Dist: pyserial>=3.5
Requires-Python: >=3.10
